artek/__init__.py
artek/eventlog/__init__.py
artek/eventlog/admin.py
artek/eventlog/mixins.py
artek/eventlog/models.py
artek/eventlog/signals.py
artek/eventlog/stats.py
artek/eventlog/tests/__init__.py
artek/eventlog/tests/tests.py
artek_eventlog-2.0.4.dist-info/METADATA
artek_eventlog-2.0.4.dist-info/WHEEL
artek_eventlog-2.0.4.dist-info/top_level.txt
artek_eventlog-2.0.4.dist-info/RECORD
